LICENSE.txt
MANIFEST.in
README.rest
setup.cfg
setup.py
django_facebook/__init__.py
django_facebook/admin.py
django_facebook/admin_actions.py
django_facebook/api.py
django_facebook/auth_backends.py
django_facebook/auth_urls.py
django_facebook/canvas.py
django_facebook/connect.py
django_facebook/context_processors.py
django_facebook/decorators.py
django_facebook/example_views.py
django_facebook/exceptions.py
django_facebook/forms.py
django_facebook/middleware.py
django_facebook/model_managers.py
django_facebook/models.py
django_facebook/registration_backends.py
django_facebook/registration_views.py
django_facebook/settings.py
django_facebook/signals.py
django_facebook/tasks.py
django_facebook/tests.py
django_facebook/urls.py
django_facebook/utils.py
django_facebook/views.py
django_facebook/fixtures/users.json
django_facebook/management/__init__.py
django_facebook/management/commands/__init__.py
django_facebook/management/commands/base.py
django_facebook/management/commands/extend_tokens.py
django_facebook/management/commands/retry_open_graph_shares.py
django_facebook/static/django_facebook/css/facebook.css
django_facebook/static/django_facebook/images/facebook_close.png
django_facebook/static/django_facebook/images/facebook_loading.gif
django_facebook/static/django_facebook/images/facebook_login.png
django_facebook/static/django_facebook/js/facebook.js
django_facebook/static/django_facebook/js/statictest.js
django_facebook/templates/django_facebook/_canvas_base.html
django_facebook/templates/django_facebook/_facebook_js.html
django_facebook/templates/django_facebook/canvas.html
django_facebook/templates/django_facebook/canvas_redirect.html
django_facebook/templates/django_facebook/connect.html
django_facebook/templates/django_facebook/example.html
django_facebook/templates/django_facebook/my_style.html
django_facebook/templates/django_facebook/page_tab.html
django_facebook/templates/django_facebook/registration.html
django_facebook/templatetags/__init__.py
wish_facebook.egg-info/PKG-INFO
wish_facebook.egg-info/SOURCES.txt
wish_facebook.egg-info/dependency_links.txt
wish_facebook.egg-info/not-zip-safe
wish_facebook.egg-info/requires.txt
wish_facebook.egg-info/top_level.txt