Metadata-Version: 1.1
Name: wish-facebook
Version: 6.0.6
Summary: Facebook open graph API client in python. Enables django applications to register users using facebook.
